README.md
setup.py
bin/convert_dizmo
dizmogen_converter/__init__.py
dizmogen_converter/exceptions.py
dizmogen_converter/generator_dizmo.py
dizmogen_converter/grace_dizmo.py
grace_dizmogen_converter.egg-info/PKG-INFO
grace_dizmogen_converter.egg-info/SOURCES.txt
grace_dizmogen_converter.egg-info/dependency_links.txt
grace_dizmogen_converter.egg-info/requires.txt
grace_dizmogen_converter.egg-info/top_level.txt