Metadata-Version: 2.1
Name: grace-dizmogen-converter
Version: 0.0.5
Summary: A script to convert grace dizmos to dizmo generator dizmos.
Home-page: UNKNOWN
Author: Michael Diener
Author-email: mdiener@dizmo.com
License: UNKNOWN
Platform: UNKNOWN
Classifier: Programming Language :: Python :: 3.5
Classifier: Operating System :: OS Independent
Classifier: Natural Language :: English
Classifier: Intended Audience :: Developers
Classifier: Environment :: Console
